var_io/__init__.py
var_io/__ioFunc.py
var_io/__var_filter.py
var_io/__var_home.py
var_io-0.2.8.dist-info/LICENSE
var_io-0.2.8.dist-info/METADATA
var_io-0.2.8.dist-info/WHEEL
var_io-0.2.8.dist-info/top_level.txt
var_io-0.2.8.dist-info/RECORD
