Metadata-Version: 2.1
Name: var-io
Version: 0.2.8
Summary: Manage your variable in jupyter
Home-page: https://github.com/karond-is-me/var-io
Author: karond
Author-email: dingyaohui.g@outlook.com
License: UNKNOWN
Platform: UNKNOWN
Classifier: Programming Language :: Python :: 3
Classifier: License :: OSI Approved :: MIT License
Classifier: Operating System :: OS Independent
Requires-Python: >=3.6
Requires-Dist: pandas (>=0.20.0)
Requires-Dist: numpy (>=1.14.0)
